INSTALL
MANIFEST.in
Makefile
README
pyvsb.conf.example
setup.py
pyvsb/__init__.py
pyvsb/backup.py
pyvsb/backuper.py
pyvsb/config.py
pyvsb/core.py
pyvsb/main.py
pyvsb/storage.py
pyvsb/utils.py
pyvsb.egg-info/PKG-INFO
pyvsb.egg-info/SOURCES.txt
pyvsb.egg-info/dependency_links.txt
pyvsb.egg-info/entry_points.txt
pyvsb.egg-info/requires.txt
pyvsb.egg-info/top_level.txt
tests/test.py
tests/root/etc/bashrc
tests/root/etc/fstab
tests/root/etc/fuse.conf
tests/root/etc/bash_completion.d/ceph
tests/root/etc/bash_completion.d/colormgr-completion.bash
tests/root/etc/bash_completion.d/createrepo.bash
tests/root/etc/bash_completion.d/dconf-bash-completion.sh
tests/root/etc/bash_completion.d/fcoeadm
tests/root/etc/bash_completion.d/fcoemon
tests/root/etc/bash_completion.d/git
tests/root/etc/bash_completion.d/grub
tests/root/etc/bash_completion.d/gvfs-bash-completion.sh
tests/root/etc/bash_completion.d/ibus.bash
tests/root/etc/bash_completion.d/pk-completion.bash
tests/root/etc/bash_completion.d/rados
tests/root/etc/bash_completion.d/rbd
tests/root/etc/bash_completion.d/redefine_filedir
tests/root/etc/bash_completion.d/semanage-bash-completion.sh
tests/root/etc/bash_completion.d/setsebool-bash-completion.sh
tests/root/etc/bash_completion.d/subversion
tests/root/etc/bash_completion.d/systemd-bash-completion.sh
tests/root/etc/bash_completion.d/udisksctl-bash-completion.sh
tests/root/etc/bash_completion.d/yum-utils.bash
tests/root/etc/bash_completion.d/yum.bash
tests/root/etc/init/ck-log-system-restart.conf
tests/root/etc/init/ck-log-system-start.conf
tests/root/etc/init/ck-log-system-stop.conf
tests/root/etc/init/system-setup-keyboard.conf
tests/root/etc/init/vpnc-cleanup.conf
tests/root/etc/profile.d/PackageKit.sh
tests/root/etc/profile.d/bash_completion.sh
tests/root/etc/profile.d/colorgrep.csh
tests/root/etc/profile.d/colorgrep.sh
tests/root/etc/profile.d/colorls.csh
tests/root/etc/profile.d/colorls.sh
tests/root/etc/profile.d/lang.csh
tests/root/etc/profile.d/lang.sh
tests/root/etc/profile.d/less.csh
tests/root/etc/profile.d/less.sh
tests/root/etc/profile.d/mc.csh
tests/root/etc/profile.d/mc.sh
tests/root/etc/profile.d/qt-graphicssystem.csh
