Metadata-Version: 1.1
Name: pyvsb
Version: 0.4.1
Summary: PyVSB - A very simple in configuring but powerful backup tool.
Home-page: https://github.com/KonishchevDmitry/pyvsb
Author: Dmitry Konishchev
Author-email: konishchev@gmail.com
License: GPL3
Platform: unix
Platform: linux
Platform: osx
Classifier: Environment :: Console
Classifier: Intended Audience :: End Users/Desktop
Classifier: Intended Audience :: System Administrators
Classifier: License :: OSI Approved :: GNU General Public License v3 (GPLv3)
Classifier: Natural Language :: English
Classifier: Operating System :: MacOS :: MacOS X
Classifier: Operating System :: POSIX
Classifier: Operating System :: Unix
Classifier: Programming Language :: Python :: 3
Classifier: Topic :: System :: Archiving :: Backup
Classifier: Topic :: Utilities
